stresampling/__init__.py
stresampling/build_bootstrap_samples.py
stresampling/confidence_interval.py
stresampling/optimal_prob.py
stresampling/stationary_bootstrap.py
stresampling-1.0.2.dist-info/LICENSE
stresampling-1.0.2.dist-info/METADATA
stresampling-1.0.2.dist-info/WHEEL
stresampling-1.0.2.dist-info/top_level.txt
stresampling-1.0.2.dist-info/RECORD
