Metadata-Version: 2.1
Name: stresampling
Version: 1.0.2
Summary: Python package for statistical analysis of time series using resampling methods
Home-page: http://github.com/YoshihikoNishikawa/stresampling
Author: Yoshihiko Nishikawa, Jun Takahashi, and Takashi Takahashi
License: GPLv3
Platform: UNKNOWN
Classifier: Development Status :: 5 - Production/Stable
Classifier: License :: OSI Approved :: GNU General Public License v3 (GPLv3)
Classifier: Operating System :: OS Independent
Classifier: Intended Audience :: Science/Research
Classifier: Topic :: Scientific/Engineering :: Physics
Classifier: Topic :: Scientific/Engineering :: Chemistry
Classifier: Topic :: Scientific/Engineering :: Artificial Intelligence
Classifier: Programming Language :: Python :: 3.6
Requires-Python: >=3.6
License-File: LICENSE
Requires-Dist: numpy (>=1.13.3)
Requires-Dist: scipy (>=0.19.1)
Requires-Dist: psutil (>=5.9.0)
